cilissa/__init__.py
cilissa/__main__.py
cilissa/classes.py
cilissa/exceptions.py
cilissa/helpers.py
cilissa/images.py
cilissa/metrics.py
cilissa/operations.py
cilissa/parsers.py
cilissa/plugins/__init__.py
cilissa/results.py
cilissa/roi.py
cilissa/transformations.py
cilissa/utils.py
cilissa-0.8.0.dist-info/LICENSE
cilissa-0.8.0.dist-info/METADATA
cilissa-0.8.0.dist-info/WHEEL
cilissa-0.8.0.dist-info/entry_points.txt
cilissa-0.8.0.dist-info/RECORD
