Metadata-Version: 2.1
Name: cilissa
Version: 0.8.0
Summary: Interactive tool for assessing digital image similarity
Home-page: https://github.com/exler/CILISSA
Author: Kamil Marut
Author-email: kamil@kamilmarut.com
Requires-Python: >=3.9,<3.12
Classifier: Environment :: Console
Classifier: Environment :: X11 Applications :: Qt
Classifier: Intended Audience :: Science/Research
Classifier: Operating System :: OS Independent
Classifier: Programming Language :: Python :: 3
Classifier: Programming Language :: Python :: 3.9
Classifier: Programming Language :: Python :: 3.10
Classifier: Programming Language :: Python :: 3.11
Classifier: Topic :: Scientific/Engineering :: Image Processing
Provides-Extra: gui
Requires-Dist: PySide6 (>=6.7.0,<7.0.0) ; extra == "gui"
Requires-Dist: numpy (>=1.26.4,<2.0.0)
Requires-Dist: opencv-python (>=4.9.0.80,<5.0.0.0)
Project-URL: Bug Tracker, https://github.com/exler/CILISSA/issues
Project-URL: Repository, https://github.com/exler/CILISSA
